LICENSE
MANIFEST.in
README.md
setup.py
avocado/__init__.py
avocado/admin.py
avocado/formatters.py
avocado/managers.py
avocado/models.py
avocado/search_indexes.py
avocado.egg-info/PKG-INFO
avocado.egg-info/SOURCES.txt
avocado.egg-info/dependency_links.txt
avocado.egg-info/pbr.json
avocado.egg-info/requires.txt
avocado.egg-info/top_level.txt
avocado/async/__init__.py
avocado/async/utils.py
avocado/conf/__init__.py
avocado/conf/global_settings.py
avocado/core/__init__.py
avocado/core/backup.py
avocado/core/loader.py
avocado/core/managers.py
avocado/core/models.py
avocado/core/structures.py
avocado/core/utils.py
avocado/core/cache/__init__.py
avocado/core/cache/managers.py
avocado/core/cache/model.py
avocado/core/cache/proxy.py
avocado/core/cache/query.py
avocado/core/cache/receivers.py
avocado/events/__init__.py
avocado/events/models.py
avocado/events/usage.py
avocado/export/__init__.py
avocado/export/_base.py
avocado/export/_csv.py
avocado/export/_excel.py
avocado/export/_html.py
avocado/export/_json.py
avocado/export/_r.py
avocado/export/_sas.py
avocado/history/__init__.py
avocado/history/managers.py
avocado/history/models.py
avocado/history/receivers.py
avocado/history/utils.py
avocado/management/__init__.py
avocado/management/base.py
avocado/management/utils.py
avocado/management/commands/__init__.py
avocado/management/commands/avocado.py
avocado/management/subcommands/__init__.py
avocado/management/subcommands/cache.py
avocado/management/subcommands/check.py
avocado/management/subcommands/data.py
avocado/management/subcommands/history.py
avocado/management/subcommands/init.py
avocado/management/subcommands/migration.py
avocado/migrations/0001_initial.py
avocado/migrations/__init__.py
avocado/query/__init__.py
avocado/query/operators.py
avocado/query/pipeline.py
avocado/query/translators.py
avocado/query/utils.py
avocado/query/validators.py
avocado/query/oldparsers/__init__.py
avocado/query/oldparsers/datacontext.py
avocado/query/oldparsers/dataquery.py
avocado/query/oldparsers/dataview.py
avocado/query/parsers/__init__.py
avocado/query/parsers/context.py
avocado/query/parsers/query.py
avocado/query/parsers/view.py
