Metadata-Version: 1.1
Name: avocado
Version: 2.4.2
Summary: Metadata APIs for Django
Home-page: http://github.com/cbmi/avocado
Author: Byron Ruth
Author-email: b@devel.io
License: BSD
Keywords: query metadata harvest orm
Platform: UNKNOWN
Classifier: Development Status :: 5 - Production/Stable
Classifier: License :: OSI Approved :: BSD License
Classifier: Programming Language :: Python :: 2.6
Classifier: Programming Language :: Python :: 2.7
Classifier: Framework :: Django
Classifier: Topic :: Internet :: WWW/HTTP
Classifier: Intended Audience :: Developers
Classifier: Intended Audience :: Science/Research
Classifier: Intended Audience :: Healthcare Industry
Classifier: Intended Audience :: Information Technology
